pytest_reraise/__init__.py
pytest_reraise/reraise.py
pytest_reraise-2.1.0.dist-info/entry_points.txt
pytest_reraise-2.1.0.dist-info/WHEEL
pytest_reraise-2.1.0.dist-info/METADATA
pytest_reraise-2.1.0.dist-info/RECORD
