Metadata-Version: 2.1
Name: pytest-reraise
Version: 2.1.0
Summary: Make multi-threaded pytest test cases fail when they should
Home-page: https://github.com/bjoluc/pytest-reraise
License: MIT
Keywords: pytest,plugin,threads,exception,assert,catch,raise,re-raise
Author: bjoluc
Author-email: mail@bjoluc.de
Requires-Python: >=3.6.1,<4.0.0
Classifier: Development Status :: 5 - Production/Stable
Classifier: Framework :: Pytest
Classifier: Intended Audience :: Developers
Classifier: License :: OSI Approved :: MIT License
Classifier: Operating System :: OS Independent
Classifier: Programming Language :: Python :: 3
Classifier: Programming Language :: Python :: 3 :: Only
Classifier: Programming Language :: Python :: 3.7
Classifier: Programming Language :: Python :: 3.8
Classifier: Programming Language :: Python :: 3.9
Classifier: Topic :: Software Development :: Libraries
Classifier: Typing :: Typed
Requires-Dist: pytest (>=4.6)
Project-URL: Documentation, https://github.com/bjoluc/pytest-reraise#readme
Project-URL: Repository, https://github.com/bjoluc/pytest-reraise
